fastapi_throttle/__init__.py
fastapi_throttle/limiter.py
fastapi_throttle/py.typed
fastapi_throttle-0.1.8.dist-info/licenses/LICENSE
tests/__init__.py
tests/test_limiter.py
fastapi_throttle-0.1.8.dist-info/METADATA
fastapi_throttle-0.1.8.dist-info/WHEEL
fastapi_throttle-0.1.8.dist-info/top_level.txt
fastapi_throttle-0.1.8.dist-info/RECORD
